README.md
setup.py
JIMG_analyst_tool/__init__.py
JIMG_analyst_tool/features_selection.py
JIMG_analyst_tool/tests.py
JIMG_analyst_tool.egg-info/PKG-INFO
JIMG_analyst_tool.egg-info/SOURCES.txt
JIMG_analyst_tool.egg-info/dependency_links.txt
JIMG_analyst_tool.egg-info/requires.txt
JIMG_analyst_tool.egg-info/top_level.txt