Metadata-Version: 2.1
Name: JIMG-analyst-tool
Version: 0.0.5
Summary: JIMG-analyst-tool
Author: Jakub Kubis
Author-email: jbiosystem@gmail.com
License: MIT
Keywords: python,nuclei,intenisty,image,high-resolution,comparison
Classifier: Development Status :: 3 - Alpha
Classifier: Programming Language :: Python :: 3
Classifier: Operating System :: MacOS :: MacOS X
Classifier: Operating System :: Microsoft :: Windows
Classifier: Operating System :: POSIX :: Linux
Requires-Python: >=3.6
